bemserver_core/__init__.py
bemserver_core/alembic.ini
bemserver_core/authorization.polar
bemserver_core/authorization.py
bemserver_core/celery.py
bemserver_core/celery_worker.py
bemserver_core/commands.py
bemserver_core/database.py
bemserver_core/email.py
bemserver_core/exceptions.py
bemserver_core/plugins.py
bemserver_core/settings.py
bemserver_core/time_utils.py
bemserver_core/utils.py
bemserver_core/common/__init__.py
bemserver_core/common/property_type.py
bemserver_core/common/units.py
bemserver_core/common/units.txt
bemserver_core/input_output/__init__.py
bemserver_core/input_output/base.py
bemserver_core/input_output/sites_io.py
bemserver_core/input_output/timeseries_data_io.py
bemserver_core/input_output/timeseries_io.py
bemserver_core/migrations/__init__.py
bemserver_core/migrations/env.py
bemserver_core/migrations/script.py.mako
bemserver_core/migrations/versions/0.10_v0_10.py
bemserver_core/migrations/versions/0.11_v0_11.py
bemserver_core/migrations/versions/0.12_v0_12.py
bemserver_core/migrations/versions/0.13_v0_13.py
bemserver_core/migrations/versions/0.14_v0_14.py
bemserver_core/migrations/versions/0.15_v0_15.py
bemserver_core/migrations/versions/0.1_v0_1.py
bemserver_core/migrations/versions/0.21_v0_21.py
bemserver_core/migrations/versions/0.3.1_v0_3.1.py
bemserver_core/migrations/versions/0.3_v0_3.py
bemserver_core/migrations/versions/0.4_v0_4.py
bemserver_core/migrations/versions/0.6_v0_6.py
bemserver_core/migrations/versions/0.8_v0_8.py
bemserver_core/model/__init__.py
bemserver_core/model/authorization.polar
bemserver_core/model/campaigns.py
bemserver_core/model/energy.py
bemserver_core/model/events.py
bemserver_core/model/notifications.py
bemserver_core/model/sites.py
bemserver_core/model/tasks.py
bemserver_core/model/timeseries.py
bemserver_core/model/timeseries_data.py
bemserver_core/model/users.py
bemserver_core/model/weather.py
bemserver_core/process/__init__.py
bemserver_core/process/cleanup.py
bemserver_core/process/completeness.py
bemserver_core-0.21.4.dist-info/entry_points.txt
bemserver_core-0.21.4.dist-info/licenses/LICENSE
bemserver_core-0.21.4.dist-info/WHEEL
bemserver_core-0.21.4.dist-info/METADATA
bemserver_core-0.21.4.dist-info/RECORD
