Metadata-Version: 2.4
Name: bemserver-core
Version: 0.21.4
Summary: BEMServer Core
Author-email: Jérôme Lafréchoux <jlafrechoux@nobatek.inef4.com>, David Frédérique <dfrederique@nobatek.inef4.com>
Maintainer-email: Jérôme Lafréchoux <jlafrechoux@nobatek.inef4.com>, David Frédérique <dfrederique@nobatek.inef4.com>
Requires-Python: >=3.9
Classifier: Development Status :: 4 - Beta
Classifier: Intended Audience :: Developers
Classifier: Topic :: Scientific/Engineering
Classifier: License :: OSI Approved :: MIT License
Classifier: Programming Language :: Python :: 3 :: Only
Classifier: Programming Language :: Python :: 3.9
Classifier: Programming Language :: Python :: 3.10
Classifier: Programming Language :: Python :: 3.11
Classifier: Programming Language :: Python :: 3.12
License-File: LICENSE
Requires-Dist: psycopg>=3.1.10,<4.0
Requires-Dist: sqlalchemy>=2.0.8,<3.0
Requires-Dist: pandas>=2.2,<3.0
Requires-Dist: pint>=0.23.0
Requires-Dist: argon2_cffi>=23.1.0
Requires-Dist: oso>=0.27.3,<0.28
Requires-Dist: alembic>=1.8.0,<2.0
Requires-Dist: click>=8.1.3,<9.0
Requires-Dist: celery>=5.3.1,<6.0
Requires-Dist: redis>=4.3.4,<5.0
Requires-Dist: requests>=2.28.2
Project-URL: Issues, https://github.com/bemserver/bemserver-core/issues
Project-URL: Source, https://github.com/bemserver/bemserver-core
